Workbook

Sheet Start Here
B1: nogvia Finance Tracker
B2: Short-term rental income & expense dashboard
B5: Quick start
B6: STEP 1 | C6: Open Settings | D6: Set currency, fiscal year, and reporting year.
B7: STEP 2 | C7: Add properties | D7: List each rental on the Properties tab.
B8: STEP 3 | C8: Log income | D8: Record bookings on the Income tab.
B9: STEP 4 | C9: Log expenses | D9: Track costs on the Expenses tab.
B10: STEP 5 | C10: Review dashboard | D10: Use the property filter and review KPIs, tables, and metrics.
B12: Tab guide
B13: Tab | C13: Purpose
B14: Dashboard | C14: Command center — KPIs, platform breakdown, performance metrics
B15: Income | C15: Booking log — nights and net revenue auto-calculate
B16: Expenses | C16: Operating costs by property and category
B17: Properties | C17: Your rental portfolio
B18: Categories | C18: Expense categories and monthly budgets
B19: Monthly P&L | C19: Month-by-month profit & loss
B20: Cashflow | C20: Cash in vs cash out by month
B21: Settings | C21: Currency, fiscal year, tax rate, RevPAR inputs
B24: Sample Q1 data is included as a demo — delete or overwrite. Gray cells are formulas; do not edit.

Sheet Settings
A1: Settings
A2: Configuration — edit values in column C
B5: Setting | C5: Value | D5: Description
B6: Default currency | C6: USD | D6: Display currency for dashboard KPIs
B7: Fiscal year start | C7: 46022.917 | D7: First day of your fiscal year
B8: Reporting year | C8: 2026 | D8: Year used for monthly reports
B9: Tax rate (%) | C9: 0 | D9: Optional — for estimated tax reserve
B10: Available nights / property / year | C10: 365 | D10: Used for RevPAR and occupancy

Sheet Properties
A1: Properties
A2: Your rental portfolio — add up to 50 properties
B4: Property Name | C4: Code | D4: Currency | E4: Bedrooms | F4: Active | G4: Notes
B5: Property 1 | C5: P1 | D5: USD | E5: 2 | F5: Yes
B6: Property 2 | C6: P2 | D6: USD | E6: 1 | F6: Yes

Sheet Categories
A1: Categories
A2: Expense categories with optional monthly budgets
B4: Category | C4: Type | D4: Monthly Budget | E4: Notes
B5: Cleaning | C5: Variable | D5: 0
B6: Maintenance | C6: Variable | D6: 0
B7: Utilities | C7: Fixed | D7: 0
B8: Insurance | C8: Fixed | D8: 0
B9: Mortgage / Rent | C9: Fixed | D9: 0
B10: Supplies | C10: Variable | D10: 0
B11: Marketing | C11: Variable | D11: 0
B12: Platform Fees | C12: Variable | D12: 0
B13: Property Tax | C13: Fixed | D13: 0
B14: HOA | C14: Fixed | D14: 0
B15: Landscaping | C15: Variable | D15: 0
B16: Pest Control | C16: Variable | D16: 0
... B20: Other | C20: Variable | D20: 0

Sheet Income
B1: Income
B2: Booking log — nights and net revenue calculate automatically
B4: Date | C4: Property | D4: Platform | E4: Check-in | F4: Check-out | G4: Nights | H4: Gross Revenue | I4: Cleaning Fee | J4: Platform Fee | K4: Other Fees | L4: Net Revenue | M4: Notes
B5: 46027 | C5: Property 1 | D5: Airbnb | E5: 46032 | F5: 46035 | G5: =IF(AND(E5<>"",F5<>""),MAX(1,F5-E5),"") | H5: 450 | I5: 75 | J5: 67.5 | K5: 0 | L5: =IF(H5="","",H5+I5-J5-K5)
B6: 46034 | C6: Property 1 | D6: VRBO | E6: 46040 | F6: 46043 | G6: =IF(AND(E6<>"",F6<>""),MAX(1,F6-E6),"") | H6: 420 | I6: 75 | J6: 50 | K6: 0 | L6: =IF(H6="","",H6+I6-J6-K6)
B7: 46042 | C7: Property 2 | D7: Direct | E7: 46047 | F7: 46050 | G7: =IF(AND(E7<>"",F7<>""),MAX(1,F7-E7),"") | H7: 380 | I7: 60 | J7: 0 | K7: 0 | L7: =IF(H7="","",H7+I7-J7-K7)
B8: 46055 | C8: Property 1 | D8: Airbnb | E8: 46061 | F8: 46065 | G8: =IF(AND(E8<>"",F8<>""),MAX(1,F8-E8),"") | H8: 620 | I8: 75 | J8: 93 | K8: 0 | L8: =IF(H8="","",H8+I8-J8-K8)
B9: 46067 | C9: Property 2 | D9: Booking.com | E9: 46071 | F9: 46074 | G9: =IF(AND(E9<>"",F9<>""),MAX(1,F9-E9),"") | H9: 410 | I9: 55 | J9: 45 | K9: 0 | L9: =IF(H9="","",H9+I9-J9-K9)
B10: 46075 | C10: Property 1 | D10: Direct | E10: 46078 | F10: 46082 | G10: =IF(AND(E10<>"",F10<>""),MAX(1,F10-E10),"") | H10: 890 | I10: 80 | J10: 0 | K10: 0 | L10: =IF(H10="","",H10+I10-J10-K10)
B11: 46086 | C11: Property 1 | D11: Airbnb | E11: 46091 | F11: 46095 | G11: =IF(AND(E11<>"",F11<>""),MAX(1,F11-E11),"") | H11: 710 | I11: 75 | J11: 106.5 | K11: 0 | L11: =IF(H11="","",H11+I11-J11-K11)
B12: 46093 | C12: Property 2 | D12: VRBO | E12: 46096 | F12: 46099 | G12: =IF(AND(E12<>"",F12<>""),MAX(1,F12-E12),"") | H12: 395 | I12: 60 | J12: 47 | K12: 0 | L12: =IF(H12="","",H12+I12-J12-K12)
B13: 46101 | C13: Property 1 | D13: Airbnb | E13: 46103 | F13: 46106 | G13: =IF(AND(E13<>"",F13<>""),MAX(1,F13-E13),"") | H13: 480 | I13: 75 | J13: 72 | K13: 0 | L13: =IF(H13="","",H13+I13-J13-K13)
B14: 46109 | C14: Property 2 | D14: Direct | E14: 46114 | F14: 46117 | G14: =IF(AND(E14<>"",F14<>""),MAX(1,F14-E14),"") | H14: 520 | I14: 60 | J14: 0 | K14: 0 | L14: =IF(H14="","",H14+I14-J14-K14)
G15: =IF(AND(E15<>"",F15<>""),MAX(1,F15-E15),"") | L15: =IF(H15="","",H15+I15-J15-K15)
G16: =IF(AND(E16<>"",F16<>""),MAX(1,F16-E16),"") | L16: =IF(H16="","",H16+I16-J16-K16)
G17: =IF(AND(E17<>"",F17<>""),MAX(1,F17-E17),"") | L17: =IF(H17="","",H17+I17-J17-K17)
G18: =IF(AND(E18<>"",F18<>""),MAX(1,F18-E18),"") | L18: =IF(H18="","",H18+I18-J18-K18)
G19: =IF(AND(E19<>"",F19<>""),MAX(1,F19-E19),"") | L19: =IF(H19="","",H19+I19-J19-K19)
G20: =IF(AND(E20<>"",F20<>""),MAX(1,F20-E20),"") | L20: =IF(H20="","",H20+I20-J20-K20)
G21: =IF(AND(E21<>"",F21<>""),MAX(1,F21-E21),"") | L21: =IF(H21="","",H21+I21-J21-K21)
G22: =IF(AND(E22<>"",F22<>""),MAX(1,F22-E22),"") | L22: =IF(H22="","",H22+I22-J22-K22)
G23: =IF(AND(E23<>"",F23<>""),MAX(1,F23-E23),"") | L23: =IF(H23="","",H23+I23-J23-K23)
G24: =IF(AND(E24<>"",F24<>""),MAX(1,F24-E24),"") | L24: =IF(H24="","",H24+I24-J24-K24)
G25: =IF(AND(E25<>"",F25<>""),MAX(1,F25-E25),"") | L25: =IF(H25="","",H25+I25-J25-K25)
G26: =IF(AND(E26<>"",F26<>""),MAX(1,F26-E26),"") | L26: =IF(H26="","",H26+I26-J26-K26)
... G504: =IF(AND(E504<>"",F504<>""),MAX(1,F504-E504),"") | L504: =IF(H504="","",H504+I504-J504-K504)

Sheet Expenses
B1: Expenses
B2: Operating costs — filter by property or category
B4: Date | C4: Property | D4: Category | E4: Vendor | F4: Amount | G4: Recurring | H4: Notes
B5: 46025 | C5: Property 1 | D5: Cleaning | E5: Clean Co | F5: 95
B6: 46030 | C6: Property 1 | D6: Utilities | E6: Power Co | F6: 142
B7: 46037 | C7: Property 2 | D7: Supplies | E7: Amazon | F7: 58
B8: 46054 | C8: Property 1 | D8: Mortgage / Rent | E8: Lender | F8: 1800
B9: 46054 | C9: Property 2 | D9: Mortgage / Rent | E9: Lender | F9: 1200
B10: 46063 | C10: Property 1 | D10: Maintenance | E10: Handyman | F10: 220
B11: 46071 | C11: Property 2 | D11: Cleaning | E11: Clean Co | F11: 85
B12: 46086 | C12: Property 1 | D12: Insurance | E12: InsureCo | F12: 310
B13: 46093 | C13: Property 2 | D13: Utilities | E13: Power Co | F13: 118
B14: 46101 | C14: Property 1 | D14: Platform Fees | E14: Airbnb | F14: 45

Sheet _calc
A2: Internal calculations — do not edit
A5: Platform | B5: YTD revenue
A6: Airbnb | B6: =IFERROR(IF(Dashboard!$C$4="All",SUMIFS(Income!$L$5:$L$504,Income!$B$5:$B$504,">="&Settings!$C$7,Income!$B$5:$B$504,"<="&DATE(Settings!$C$8,12,31),Income!$D$5:$D$504,"Airbnb"),SUMIFS(Income!$L$5:$L$504,Income!$B$5:$B$504,">="&Settings!$C$7,Income!$B$5:$B$504,"<="&DATE(Settings!$C$8,12,31),Income!$D$5:$D$504,"Airbnb",Income!$C$5:$C$504,Dashboard!$C$4)),0)
A7: VRBO | B7: =IFERROR(IF(Dashboard!$C$4="All",SUMIFS(Income!$L$5:$L$504,Income!$B$5:$B$504,">="&Settings!$C$7,Income!$B$5:$B$504,"<="&DATE(Settings!$C$8,12,31),Income!$D$5:$D$504,"VRBO"),SUMIFS(Income!$L$5:$L$504,Income!$B$5:$B$504,">="&Settings!$C$7,Income!$B$5:$B$504,"<="&DATE(Settings!$C$8,12,31),Income!$D$5:$D$504,"VRBO",Income!$C$5:$C$504,Dashboard!$C$4)),0)
A8: Booking.com | B8: =IFERROR(IF(Dashboard!$C$4="All",SUMIFS(Income!$L$5:$L$504,Income!$B$5:$B$504,">="&Settings!$C$7,Income!$B$5:$B$504,"<="&DATE(Settings!$C$8,12,31),Income!$D$5:$D$504,"Booking.com"),SUMIFS(Income!$L$5:$L$504,Income!$B$5:$B$504,">="&Settings!$C$7,Income!$B$5:$B$504,"<="&DATE(Settings!$C$8,12,31),Income!$D$5:$D$504,"Booking.com",Income!$C$5:$C$504,Dashboard!$C$4)),0)
A9: Direct | B9: =IFERROR(IF(Dashboard!$C$4="All",SUMIFS(Income!$L$5:$L$504,Income!$B$5:$B$504,">="&Settings!$C$7,Income!$B$5:$B$504,"<="&DATE(Settings!$C$8,12,31),Income!$D$5:$D$504,"Direct"),SUMIFS(Income!$L$5:$L$504,Income!$B$5:$B$504,">="&Settings!$C$7,Income!$B$5:$B$504,"<="&DATE(Settings!$C$8,12,31),Income!$D$5:$D$504,"Direct",Income!$C$5:$C$504,Dashboard!$C$4)),0)
A10: Other | B10: =IFERROR(IF(Dashboard!$C$4="All",SUMIFS(Income!$L$5:$L$504,Income!$B$5:$B$504,">="&Settings!$C$7,Income!$B$5:$B$504,"<="&DATE(Settings!$C$8,12,31),Income!$D$5:$D$504,"Other"),SUMIFS(Income!$L$5:$L$504,Income!$B$5:$B$504,">="&Settings!$C$7,Income!$B$5:$B$504,"<="&DATE(Settings!$C$8,12,31),Income!$D$5:$D$504,"Other",Income!$C$5:$C$504,Dashboard!$C$4)),0)
A14: Platform | B14: Jan | C14: Feb | D14: Mar | E14: Apr | F14: May | G14: Jun | H14: Jul | I14: Aug | J14: Sep | K14: Oct | L14: Nov | M14: Dec | N14: Total
A15: Airbnb | B15: =IFERROR(IF(Dashboard!$C$4="All",SUMIFS(Income!$L$5:$L$504,Income!$B$5:$B$504,">="&DATE(Settings!$C$8,1,1),Income!$B$5:$B$504,"<="&EOMONTH(DATE(Settings!$C$8,1,1),0),Income!$D$5:$D$504,"Airbnb"),SUMIFS(Income!$L$5:$L$504,Income!$B$5:$B$504,">="&DATE(Settings!$C$8,1,1),Income!$B$5:$B$504,"<="&EOMONTH(DATE(Settings!$C$8,1,1),0),Income!$D$5:$D$504,"Airbnb",Income!$C$5:$C$504,Dashboard!$C$4)),0) | C15: =IFERROR(IF(Dashboard!$C$4="All",SUMIFS(Income!$L$5:$L$504,Income!$B$5:$B$504,">="&DATE(Settings!$C$8,2,1),Income!$B$5:$B$504,"<="&EOMONTH(DATE(Settings!$C$8,2,1),0),Income!$D$5:$D$504,"Airbnb"),SUMIFS(Income!$L$5:$L$504,Income!$B$5:$B$504,">="&DATE(Settings!$C$8,2,1),Income!$B$5:$B$504,"<="&EOMONTH(DATE(Settings!$C$8,2,1),0),Income!$D$5:$D$504,"Airbnb",Income!$C$5:$C$504,Dashboard!$C$4)),0) | D15: =IFERROR(IF(Dashboard!$C$4="All",SUMIFS(Income!$L$5:$L$504,Income!$B$5:$B$504,">="&DATE(Settings!$C$8,3,1),Income!$B$5:$B$504,"<="&EOMONTH(DATE(Settings!$C$8,3,1),0),Income!$D$5:$D$504,"Airbnb"),SUMIFS(Income!$L$5:$L$504,Income!$B$5:$B$504,">="&DATE(Settings!$C$8,3,1),Income!$B$5:$B$504,"<="&EOMONTH(DATE(Settings!$C$8,3,1),0),Income!$D$5:$D$504,"Airbnb",Income!$C$5:$C$504,Dashboard!$C$4)),0) | E15: =IFERROR(IF(Dashboard!$C$4="All",SUMIFS(Income!$L$5:$L$504,Income!$B$5:$B$504,">="&DATE(Settings!$C$8,4,1),Income!$B$5:$B$504,"<="&EOMONTH(DATE(Settings!$C$8,4,1),0),Income!$D$5:$D$504,"Airbnb"),SUMIFS(Income!$L$5:$L$504,Income!$B$5:$B$504,">="&DATE(Settings!$C$8,4,1),Income!$B$5:$B$504,"<="&EOMONTH(DATE(Settings!$C$8,4,1),0),Income!$D$5:$D$504,"Airbnb",Income!$C$5:$C$504,Dashboard!$C$4)),0) | F15: =IFERROR(IF(Dashboard!$C$4="All",SUMIFS(Income!$L$5:$L$504,Income!$B$5:$B$504,">="&DATE(Settings!$C$8,5,1),Income!$B$5:$B$504,"<="&EOMONTH(DATE(Settings!$C$8,5,1),0),Income!$D$5:$D$504,"Airbnb"),SUMIFS(Income!$L$5:$L$504,Income!$B$5:$B$504,">="&DATE(Settings!$C$8,5,1),Income!$B$5:$B$504,"<="&EOMONTH(DATE(Settings!$C$8,5,1),0),Income!$D$5:$D$504,"Airbnb",Income!$C$5:$C$504,Dashboard!$C$4)),0) | G15: =IFERROR(IF(Dashboard!$C$4="All",SUMIFS(Income!$L$5:$L$504,Income!$B$5:$B$504,">="&DATE(Settings!$C$8,6,1),Income!$B$5:$B$504,"<="&EOMONTH(DATE(Settings!$C$8,6,1),0),Income!$D$5:$D$504,"Airbnb"),SUMIFS(Income!$L$5:$L$504,Income!$B$5:$B$504,">="&DATE(Settings!$C$8,6,1),Income!$B$5:$B$504,"<="&EOMONTH(DATE(Settings!$C$8,6,1),0),Income!$D$5:$D$504,"Airbnb",Income!$C$5:$C$504,Dashboard!$C$4)),0) | H15: =IFERROR(IF(Dashboard!$C$4="All",SUMIFS(Income!$L$5:$L$504,Income!$B$5:$B$504,">="&DATE(Settings!$C$8,7,1),Income!$B$5:$B$504,"<="&EOMONTH(DATE(Settings!$C$8,7,1),0),Income!$D$5:$D$504,"Airbnb"),SUMIFS(Income!$L$5:$L$504,Income!$B$5:$B$504,">="&DATE(Settings!$C$8,7,1),Income!$B$5:$B$504,"<="&EOMONTH(DATE(Settings!$C$8,7,1),0),Income!$D$5:$D$504,"Airbnb",Income!$C$5:$C$504,Dashboard!$C$4)),0) | I15: =IFERROR(IF(Dashboard!$C$4="All",SUMIFS(Income!$L$5:$L$504,Income!$B$5:$B$504,">="&DATE(Settings!$C$8,8,1),Income!$B$5:$B$504,"<="&EOMONTH(DATE(Settings!$C$8,8,1),0),Income!$D$5:$D$504,"Airbnb"),SUMIFS(Income!$L$5:$L$504,Income!$B$5:$B$504,">="&DATE(Settings!$C$8,8,1),Income!$B$5:$B$504,"<="&EOMONTH(DATE(Settings!$C$8,8,1),0),Income!$D$5:$D$504,"Airbnb",Income!$C$5:$C$504,Dashboard!$C$4)),0) | J15: =IFERROR(IF(Dashboard!$C$4="All",SUMIFS(Income!$L$5:$L$504,Income!$B$5:$B$504,">="&DATE(Settings!$C$8,9,1),Income!$B$5:$B$504,"<="&EOMONTH(DATE(Settings!$C$8,9,1),0),Income!$D$5:$D$504,"Airbnb"),SUMIFS(Income!$L$5:$L$504,Income!$B$5:$B$504,">="&DATE(Settings!$C$8,9,1),Income!$B$5:$B$504,"<="&EOMONTH(DATE(Settings!$C$8,9,1),0),Income!$D$5:$D$504,"Airbnb",Income!$C$5:$C$504,Dashboard!$C$4)),0) | K15: =IFERROR(IF(Dashboard!$C$4="All",SUMIFS(Income!$L$5:$L$504,Income!$B$5:$B$504,">="&DATE(Settings!$C$8,10,1),Income!$B$5:$B$504,"<="&EOMONTH(DATE(Settings!$C$8,10,1),0),Income!$D$5:$D$504,"Airbnb"),SUMIFS(Income!$L$5:$L$504,Income!$B$5:$B$504,">="&DATE(Settings!$C$8,10,1),Income!$B$5:$B$504,"<="&EOMONTH(DATE(Settings!$C$8,10,1),0),Income!$D$5:$D$504,"Airbnb",Income!$C$5:$C$504,Dashboard!$C$4)),0) | L15: =IFERROR(IF(Dashboard!$C$4="All",SUMIFS(Income!$L$5:$L$504,Income!$B$5:$B$504,">="&DATE(Settings!$C$8,11,1),Income!$B$5:$B$504,"<="&EOMONTH(DATE(Settings!$C$8,11,1),0),Income!$D$5:$D$504,"Airbnb"),SUMIFS(Income!$L$5:$L$504,Income!$B$5:$B$504,">="&DATE(Settings!$C$8,11,1),Income!$B$5:$B$504,"<="&EOMONTH(DATE(Settings!$C$8,11,1),0),Income!$D$5:$D$504,"Airbnb",Income!$C$5:$C$504,Dashboard!$C$4)),0) | M15: =IFERROR(IF(Dashboard!$C$4="All",SUMIFS(Income!$L$5:$L$504,Income!$B$5:$B$504,">="&DATE(Settings!$C$8,12,1),Income!$B$5:$B$504,"<="&EOMONTH(DATE(Settings!$C$8,12,1),0),Income!$D$5:$D$504,"Airbnb"),SUMIFS(Income!$L$5:$L$504,Income!$B$5:$B$504,">="&DATE(Settings!$C$8,12,1),Income!$B$5:$B$504,"<="&EOMONTH(DATE(Settings!$C$8,12,1),0),Income!$D$5:$D$504,"Airbnb",Income!$C$5:$C$504,Dashboard!$C$4)),0) | N15: =SUM(B15:M15)
A16: VRBO | B16: =IFERROR(IF(Dashboard!$C$4="All",SUMIFS(Income!$L$5:$L$504,Income!$B$5:$B$504,">="&DATE(Settings!$C$8,1,1),Income!$B$5:$B$504,"<="&EOMONTH(DATE(Settings!$C$8,1,1),0),Income!$D$5:$D$504,"VRBO"),SUMIFS(Income!$L$5:$L$504,Income!$B$5:$B$504,">="&DATE(Settings!$C$8,1,1),Income!$B$5:$B$504,"<="&EOMONTH(DATE(Settings!$C$8,1,1),0),Income!$D$5:$D$504,"VRBO",Income!$C$5:$C$504,Dashboard!$C$4)),0) | C16: =IFERROR(IF(Dashboard!$C$4="All",SUMIFS(Income!$L$5:$L$504,Income!$B$5:$B$504,">="&DATE(Settings!$C$8,2,1),Income!$B$5:$B$504,"<="&EOMONTH(DATE(Settings!$C$8,2,1),0),Income!$D$5:$D$504,"VRBO"),SUMIFS(Income!$L$5:$L$504,Income!$B$5:$B$504,">="&DATE(Settings!$C$8,2,1),Income!$B$5:$B$504,"<="&EOMONTH(DATE(Settings!$C$8,2,1),0),Income!$D$5:$D$504,"VRBO",Income!$C$5:$C$504,Dashboard!$C$4)),0) | D16: =IFERROR(IF(Dashboard!$C$4="All",SUMIFS(Income!$L$5:$L$504,Income!$B$5:$B$504,">="&DATE(Settings!$C$8,3,1),Income!$B$5:$B$504,"<="&EOMONTH(DATE(Settings!$C$8,3,1),0),Income!$D$5:$D$504,"VRBO"),SUMIFS(Income!$L$5:$L$504,Income!$B$5:$B$504,">="&DATE(Settings!$C$8,3,1),Income!$B$5:$B$504,"<="&EOMONTH(DATE(Settings!$C$8,3,1),0),Income!$D$5:$D$504,"VRBO",Income!$C$5:$C$504,Dashboard!$C$4)),0) | E16: =IFERROR(IF(Dashboard!$C$4="All",SUMIFS(Income!$L$5:$L$504,Income!$B$5:$B$504,">="&DATE(Settings!$C$8,4,1),Income!$B$5:$B$504,"<="&EOMONTH(DATE(Settings!$C$8,4,1),0),Income!$D$5:$D$504,"VRBO"),SUMIFS(Income!$L$5:$L$504,Income!$B$5:$B$504,">="&DATE(Settings!$C$8,4,1),Income!$B$5:$B$504,"<="&EOMONTH(DATE(Settings!$C$8,4,1),0),Income!$D$5:$D$504,"VRBO",Income!$C$5:$C$504,Dashboard!$C$4)),0) | F16: =IFERROR(IF(Dashboard!$C$4="All",SUMIFS(Income!$L$5:$L$504,Income!$B$5:$B$504,">="&DATE(Settings!$C$8,5,1),Income!$B$5:$B$504,"<="&EOMONTH(DATE(Settings!$C$8,5,1),0),Income!$D$5:$D$504,"VRBO"),SUMIFS(Income!$L$5:$L$504,Income!$B$5:$B$504,">="&DATE(Settings!$C$8,5,1),Income!$B$5:$B$504,"<="&EOMONTH(DATE(Settings!$C$8,5,1),0),Income!$D$5:$D$504,"VRBO",Income!$C$5:$C$504,Dashboard!$C$4)),0) | G16: =IFERROR(IF(Dashboard!$C$4="All",SUMIFS(Income!$L$5:$L$504,Income!$B$5:$B$504,">="&DATE(Settings!$C$8,6,1),Income!$B$5:$B$504,"<="&EOMONTH(DATE(Settings!$C$8,6,1),0),Income!$D$5:$D$504,"VRBO"),SUMIFS(Income!$L$5:$L$504,Income!$B$5:$B$504,">="&DATE(Settings!$C$8,6,1),Income!$B$5:$B$504,"<="&EOMONTH(DATE(Settings!$C$8,6,1),0),Income!$D$5:$D$504,"VRBO",Income!$C$5:$C$504,Dashboard!$C$4)),0) | H16: =IFERROR(IF(Dashboard!$C$4="All",SUMIFS(Income!$L$5:$L$504,Income!$B$5:$B$504,">="&DATE(Settings!$C$8,7,1),Income!$B$5:$B$504,"<="&EOMONTH(DATE(Settings!$C$8,7,1),0),Income!$D$5:$D$504,"VRBO"),SUMIFS(Income!$L$5:$L$504,Income!$B$5:$B$504,">="&DATE(Settings!$C$8,7,1),Income!$B$5:$B$504,"<="&EOMONTH(DATE(Settings!$C$8,7,1),0),Income!$D$5:$D$504,"VRBO",Income!$C$5:$C$504,Dashboard!$C$4)),0) | I16: =IFERROR(IF(Dashboard!$C$4="All",SUMIFS(Income!$L$5:$L$504,Income!$B$5:$B$504,">="&DATE(Settings!$C$8,8,1),Income!$B$5:$B$504,"<="&EOMONTH(DATE(Settings!$C$8,8,1),0),Income!$D$5:$D$504,"VRBO"),SUMIFS(Income!$L$5:$L$504,Income!$B$5:$B$504,">="&DATE(Settings!$C$8,8,1),Income!$B$5:$B$504,"<="&EOMONTH(DATE(Settings!$C$8,8,1),0),Income!$D$5:$D$504,"VRBO",Income!$C$5:$C$504,Dashboard!$C$4)),0) | J16: =IFERROR(IF(Dashboard!$C$4="All",SUMIFS(Income!$L$5:$L$504,Income!$B$5:$B$504,">="&DATE(Settings!$C$8,9,1),Income!$B$5:$B$504,"<="&EOMONTH(DATE(Settings!$C$8,9,1),0),Income!$D$5:$D$504,"VRBO"),SUMIFS(Income!$L$5:$L$504,Income!$B$5:$B$504,">="&DATE(Settings!$C$8,9,1),Income!$B$5:$B$504,"<="&EOMONTH(DATE(Settings!$C$8,9,1),0),Income!$D$5:$D$504,"VRBO",Income!$C$5:$C$504,Dashboard!$C$4)),0) | K16: =IFERROR(IF(Dashboard!$C$4="All",SUMIFS(Income!$L$5:$L$504,Income!$B$5:$B$504,">="&DATE(Settings!$C$8,10,1),Income!$B$5:$B$504,"<="&EOMONTH(DATE(Settings!$C$8,10,1),0),Income!$D$5:$D$504,"VRBO"),SUMIFS(Income!$L$5:$L$504,Income!$B$5:$B$504,">="&DATE(Settings!$C$8,10,1),Income!$B$5:$B$504,"<="&EOMONTH(DATE(Settings!$C$8,10,1),0),Income!$D$5:$D$504,"VRBO",Income!$C$5:$C$504,Dashboard!$C$4)),0) | L16: =IFERROR(IF(Dashboard!$C$4="All",SUMIFS(Income!$L$5:$L$504,Income!$B$5:$B$504,">="&DATE(Settings!$C$8,11,1),Income!$B$5:$B$504,"<="&EOMONTH(DATE(Settings!$C$8,11,1),0),Income!$D$5:$D$504,"VRBO"),SUMIFS(Income!$L$5:$L$504,Income!$B$5:$B$504,">="&DATE(Settings!$C$8,11,1),Income!$B$5:$B$504,"<="&EOMONTH(DATE(Settings!$C$8,11,1),0),Income!$D$5:$D$504,"VRBO",Income!$C$5:$C$504,Dashboard!$C$4)),0) | M16: =IFERROR(IF(Dashboard!$C$4="All",SUMIFS(Income!$L$5:$L$504,Income!$B$5:$B$504,">="&DATE(Settings!$C$8,12,1),Income!$B$5:$B$504,"<="&EOMONTH(DATE(Settings!$C$8,12,1),0),Income!$D$5:$D$504,"VRBO"),SUMIFS(Income!$L$5:$L$504,Income!$B$5:$B$504,">="&DATE(Settings!$C$8,12,1),Income!$B$5:$B$504,"<="&EOMONTH(DATE(Settings!$C$8,12,1),0),Income!$D$5:$D$504,"VRBO",Income!$C$5:$C$504,Dashboard!$C$4)),0) | N16: =SUM(B16:M16)
A17: Booking.com | B17: =IFERROR(IF(Dashboard!$C$4="All",SUMIFS(Income!$L$5:$L$504,Income!$B$5:$B$504,">="&DATE(Settings!$C$8,1,1),Income!$B$5:$B$504,"<="&EOMONTH(DATE(Settings!$C$8,1,1),0),Income!$D$5:$D$504,"Booking.com"),SUMIFS(Income!$L$5:$L$504,Income!$B$5:$B$504,">="&DATE(Settings!$C$8,1,1),Income!$B$5:$B$504,"<="&EOMONTH(DATE(Settings!$C$8,1,1),0),Income!$D$5:$D$504,"Booking.com",Income!$C$5:$C$504,Dashboard!$C$4)),0) | C17: =IFERROR(IF(Dashboard!$C$4="All",SUMIFS(Income!$L$5:$L$504,Income!$B$5:$B$504,">="&DATE(Settings!$C$8,2,1),Income!$B$5:$B$504,"<="&EOMONTH(DATE(Settings!$C$8,2,1),0),Income!$D$5:$D$504,"Booking.com"),SUMIFS(Income!$L$5:$L$504,Income!$B$5:$B$504,">="&DATE(Settings!$C$8,2,1),Income!$B$5:$B$504,"<="&EOMONTH(DATE(Settings!$C$8,2,1),0),Income!$D$5:$D$504,"Booking.com",Income!$C$5:$C$504,Dashboard!$C$4)),0) | D17: =IFERROR(IF(Dashboard!$C$4="All",SUMIFS(Income!$L$5:$L$504,Income!$B$5:$B$504,">="&DATE(Settings!$C$8,3,1),Income!$B$5:$B$504,"<="&EOMONTH(DATE(Settings!$C$8,3,1),0),Income!$D$5:$D$504,"Booking.com"),SUMIFS(Income!$L$5:$L$504,Income!$B$5:$B$504,">="&DATE(Settings!$C$8,3,1),Income!$B$5:$B$504,"<="&EOMONTH(DATE(Settings!$C$8,3,1),0),Income!$D$5:$D$504,"Booking.com",Income!$C$5:$C$504,Dashboard!$C$4)),0) | E17: =IFERROR(IF(Dashboard!$C$4="All",SUMIFS(Income!$L$5:$L$504,Income!$B$5:$B$504,">="&DATE(Settings!$C$8,4,1),Income!$B$5:$B$504,"<="&EOMONTH(DATE(Settings!$C$8,4,1),0),Income!$D$5:$D$504,"Booking.com"),SUMIFS(Income!$L$5:$L$504,Income!$B$5:$B$504,">="&DATE(Settings!$C$8,4,1),Income!$B$5:$B$504,"<="&EOMONTH(DATE(Settings!$C$8,4,1),0),Income!$D$5:$D$504,"Booking.com",Income!$C$5:$C$504,Dashboard!$C$4)),0) | F17: =IFERROR(IF(Dashboard!$C$4="All",SUMIFS(Income!$L$5:$L$504,Income!$B$5:$B$504,">="&DATE(Settings!$C$8,5,1),Income!$B$5:$B$504,"<="&EOMONTH(DATE(Settings!$C$8,5,1),0),Income!$D$5:$D$504,"Booking.com"),SUMIFS(Income!$L$5:$L$504,Income!$B$5:$B$504,">="&DATE(Settings!$C$8,5,1),Income!$B$5:$B$504,"<="&EOMONTH(DATE(Settings!$C$8,5,1),0),Income!$D$5:$D$504,"Booking.com",Income!$C$5:$C$504,Dashboard!$C$4)),0) | G17: =IFERROR(IF(Dashboard!$C$4="All",SUMIFS(Income!$L$5:$L$504,Income!$B$5:$B$504,">="&DATE(Settings!$C$8,6,1),Income!$B$5:$B$504,"<="&EOMONTH(DATE(Settings!$C$8,6,1),0),Income!$D$5:$D$504,"Booking.com"),SUMIFS(Income!$L$5:$L$504,Income!$B$5:$B$504,">="&DATE(Settings!$C$8,6,1),Income!$B$5:$B$504,"<="&EOMONTH(DATE(Settings!$C$8,6,1),0),Income!$D$5:$D$504,"Booking.com",Income!$C$5:$C$504,Dashboard!$C$4)),0) | H17: =IFERROR(IF(Dashboard!$C$4="All",SUMIFS(Income!$L$5:$L$504,Income!$B$5:$B$504,">="&DATE(Settings!$C$8,7,1),Income!$B$5:$B$504,"<="&EOMONTH(DATE(Settings!$C$8,7,1),0),Income!$D$5:$D$504,"Booking.com"),SUMIFS(Income!$L$5:$L$504,Income!$B$5:$B$504,">="&DATE(Settings!$C$8,7,1),Income!$B$5:$B$504,"<="&EOMONTH(DATE(Settings!$C$8,7,1),0),Income!$D$5:$D$504,"Booking.com",Income!$C$5:$C$504,Dashboard!$C$4)),0) | I17: =IFERROR(IF(Dashboard!$C$4="All",SUMIFS(Income!$L$5:$L$504,Income!$B$5:$B$504,">="&DATE(Settings!$C$8,8,1),Income!$B$5:$B$504,"<="&EOMONTH(DATE(Settings!$C$8,8,1),0),Income!$D$5:$D$504,"Booking.com"),SUMIFS(Income!$L$5:$L$504,Income!$B$5:$B$504,">="&DATE(Settings!$C$8,8,1),Income!$B$5:$B$504,"<="&EOMONTH(DATE(Settings!$C$8,8,1),0),Income!$D$5:$D$504,"Booking.com",Income!$C$5:$C$504,Dashboard!$C$4)),0) | J17: =IFERROR(IF(Dashboard!$C$4="All",SUMIFS(Income!$L$5:$L$504,Income!$B$5:$B$504,">="&DATE(Settings!$C$8,9,1),Income!$B$5:$B$504,"<="&EOMONTH(DATE(Settings!$C$8,9,1),0),Income!$D$5:$D$504,"Booking.com"),SUMIFS(Income!$L$5:$L$504,Income!$B$5:$B$504,">="&DATE(Settings!$C$8,9,1),Income!$B$5:$B$504,"<="&EOMONTH(DATE(Settings!$C$8,9,1),0),Income!$D$5:$D$504,"Booking.com",Income!$C$5:$C$504,Dashboard!$C$4)),0) | K17: =IFERROR(IF(Dashboard!$C$4="All",SUMIFS(Income!$L$5:$L$504,Income!$B$5:$B$504,">="&DATE(Settings!$C$8,10,1),Income!$B$5:$B$504,"<="&EOMONTH(DATE(Settings!$C$8,10,1),0),Income!$D$5:$D$504,"Booking.com"),SUMIFS(Income!$L$5:$L$504,Income!$B$5:$B$504,">="&DATE(Settings!$C$8,10,1),Income!$B$5:$B$504,"<="&EOMONTH(DATE(Settings!$C$8,10,1),0),Income!$D$5:$D$504,"Booking.com",Income!$C$5:$C$504,Dashboard!$C$4)),0) | L17: =IFERROR(IF(Dashboard!$C$4="All",SUMIFS(Income!$L$5:$L$504,Income!$B$5:$B$504,">="&DATE(Settings!$C$8,11,1),Income!$B$5:$B$504,"<="&EOMONTH(DATE(Settings!$C$8,11,1),0),Income!$D$5:$D$504,"Booking.com"),SUMIFS(Income!$L$5:$L$504,Income!$B$5:$B$504,">="&DATE(Settings!$C$8,11,1),Income!$B$5:$B$504,"<="&EOMONTH(DATE(Settings!$C$8,11,1),0),Income!$D$5:$D$504,"Booking.com",Income!$C$5:$C$504,Dashboard!$C$4)),0) | M17: =IFERROR(IF(Dashboard!$C$4="All",SUMIFS(Income!$L$5:$L$504,Income!$B$5:$B$504,">="&DATE(Settings!$C$8,12,1),Income!$B$5:$B$504,"<="&EOMONTH(DATE(Settings!$C$8,12,1),0),Income!$D$5:$D$504,"Booking.com"),SUMIFS(Income!$L$5:$L$504,Income!$B$5:$B$504,">="&DATE(Settings!$C$8,12,1),Income!$B$5:$B$504,"<="&EOMONTH(DATE(Settings!$C$8,12,1),0),Income!$D$5:$D$504,"Booking.com",Income!$C$5:$C$504,Dashboard!$C$4)),0) | N17: =SUM(B17:M17)
A18: Direct | B18: =IFERROR(IF(Dashboard!$C$4="All",SUMIFS(Income!$L$5:$L$504,Income!$B$5:$B$504,">="&DATE(Settings!$C$8,1,1),Income!$B$5:$B$504,"<="&EOMONTH(DATE(Settings!$C$8,1,1),0),Income!$D$5:$D$504,"Direct"),SUMIFS(Income!$L$5:$L$504,Income!$B$5:$B$504,">="&DATE(Settings!$C$8,1,1),Income!$B$5:$B$504,"<="&EOMONTH(DATE(Settings!$C$8,1,1),0),Income!$D$5:$D$504,"Direct",Income!$C$5:$C$504,Dashboard!$C$4)),0) | C18: =IFERROR(IF(Dashboard!$C$4="All",SUMIFS(Income!$L$5:$L$504,Income!$B$5:$B$504,">="&DATE(Settings!$C$8,2,1),Income!$B$5:$B$504,"<="&EOMONTH(DATE(Settings!$C$8,2,1),0),Income!$D$5:$D$504,"Direct"),SUMIFS(Income!$L$5:$L$504,Income!$B$5:$B$504,">="&DATE(Settings!$C$8,2,1),Income!$B$5:$B$504,"<="&EOMONTH(DATE(Settings!$C$8,2,1),0),Income!$D$5:$D$504,"Direct",Income!$C$5:$C$504,Dashboard!$C$4)),0) | D18: =IFERROR(IF(Dashboard!$C$4="All",SUMIFS(Income!$L$5:$L$504,Income!$B$5:$B$504,">="&DATE(Settings!$C$8,3,1),Income!$B$5:$B$504,"<="&EOMONTH(DATE(Settings!$C$8,3,1),0),Income!$D$5:$D$504,"Direct"),SUMIFS(Income!$L$5:$L$504,Income!$B$5:$B$504,">="&DATE(Settings!$C$8,3,1),Income!$B$5:$B$504,"<="&EOMONTH(DATE(Settings!$C$8,3,1),0),Income!$D$5:$D$504,"Direct",Income!$C$5:$C$504,Dashboard!$C$4)),0) | E18: =IFERROR(IF(Dashboard!$C$4="All",SUMIFS(Income!$L$5:$L$504,Income!$B$5:$B$504,">="&DATE(Settings!$C$8,4,1),Income!$B$5:$B$504,"<="&EOMONTH(DATE(Settings!$C$8,4,1),0),Income!$D$5:$D$504,"Direct"),SUMIFS(Income!$L$5:$L$504,Income!$B$5:$B$504,">="&DATE(Settings!$C$8,4,1),Income!$B$5:$B$504,"<="&EOMONTH(DATE(Settings!$C$8,4,1),0),Income!$D$5:$D$504,"Direct",Income!$C$5:$C$504,Dashboard!$C$4)),0) | F18: =IFERROR(IF(Dashboard!$C$4="All",SUMIFS(Income!$L$5:$L$504,Income!$B$5:$B$504,">="&DATE(Settings!$C$8,5,1),Income!$B$5:$B$504,"<="&EOMONTH(DATE(Settings!$C$8,5,1),0),Income!$D$5:$D$504,"Direct"),SUMIFS(Income!$L$5:$L$504,Income!$B$5:$B$504,">="&DATE(Settings!$C$8,5,1),Income!$B$5:$B$504,"<="&EOMONTH(DATE(Settings!$C$8,5,1),0),Income!$D$5:$D$504,"Direct",Income!$C$5:$C$504,Dashboard!$C$4)),0) | G18: =IFERROR(IF(Dashboard!$C$4="All",SUMIFS(Income!$L$5:$L$504,Income!$B$5:$B$504,">="&DATE(Settings!$C$8,6,1),Income!$B$5:$B$504,"<="&EOMONTH(DATE(Settings!$C$8,6,1),0),Income!$D$5:$D$504,"Direct"),SUMIFS(Income!$L$5:$L$504,Income!$B$5:$B$504,">="&DATE(Settings!$C$8,6,1),Income!$B$5:$B$504,"<="&EOMONTH(DATE(Settings!$C$8,6,1),0),Income!$D$5:$D$504,"Direct",Income!$C$5:$C$504,Dashboard!$C$4)),0) | H18: =IFERROR(IF(Dashboard!$C$4="All",SUMIFS(Income!$L$5:$L$504,Income!$B$5:$B$504,">="&DATE(Settings!$C$8,7,1),Income!$B$5:$B$504,"<="&EOMONTH(DATE(Settings!$C$8,7,1),0),Income!$D$5:$D$504,"Direct"),SUMIFS(Income!$L$5:$L$504,Income!$B$5:$B$504,">="&DATE(Settings!$C$8,7,1),Income!$B$5:$B$504,"<="&EOMONTH(DATE(Settings!$C$8,7,1),0),Income!$D$5:$D$504,"Direct",Income!$C$5:$C$504,Dashboard!$C$4)),0) | I18: =IFERROR(IF(Dashboard!$C$4="All",SUMIFS(Income!$L$5:$L$504,Income!$B$5:$B$504,">="&DATE(Settings!$C$8,8,1),Income!$B$5:$B$504,"<="&EOMONTH(DATE(Settings!$C$8,8,1),0),Income!$D$5:$D$504,"Direct"),SUMIFS(Income!$L$5:$L$504,Income!$B$5:$B$504,">="&DATE(Settings!$C$8,8,1),Income!$B$5:$B$504,"<="&EOMONTH(DATE(Settings!$C$8,8,1),0),Income!$D$5:$D$504,"Direct",Income!$C$5:$C$504,Dashboard!$C$4)),0) | J18: =IFERROR(IF(Dashboard!$C$4="All",SUMIFS(Income!$L$5:$L$504,Income!$B$5:$B$504,">="&DATE(Settings!$C$8,9,1),Income!$B$5:$B$504,"<="&EOMONTH(DATE(Settings!$C$8,9,1),0),Income!$D$5:$D$504,"Direct"),SUMIFS(Income!$L$5:$L$504,Income!$B$5:$B$504,">="&DATE(Settings!$C$8,9,1),Income!$B$5:$B$504,"<="&EOMONTH(DATE(Settings!$C$8,9,1),0),Income!$D$5:$D$504,"Direct",Income!$C$5:$C$504,Dashboard!$C$4)),0) | K18: =IFERROR(IF(Dashboard!$C$4="All",SUMIFS(Income!$L$5:$L$504,Income!$B$5:$B$504,">="&DATE(Settings!$C$8,10,1),Income!$B$5:$B$504,"<="&EOMONTH(DATE(Settings!$C$8,10,1),0),Income!$D$5:$D$504,"Direct"),SUMIFS(Income!$L$5:$L$504,Income!$B$5:$B$504,">="&DATE(Settings!$C$8,10,1),Income!$B$5:$B$504,"<="&EOMONTH(DATE(Settings!$C$8,10,1),0),Income!$D$5:$D$504,"Direct",Income!$C$5:$C$504,Dashboard!$C$4)),0) | L18: =IFERROR(IF(Dashboard!$C$4="All",SUMIFS(Income!$L$5:$L$504,Income!$B$5:$B$504,">="&DATE(Settings!$C$8,11,1),Income!$B$5:$B$504,"<="&EOMONTH(DATE(Settings!$C$8,11,1),0),Income!$D$5:$D$504,"Direct"),SUMIFS(Income!$L$5:$L$504,Income!$B$5:$B$504,">="&DATE(Settings!$C$8,11,1),Income!$B$5:$B$504,"<="&EOMONTH(DATE(Settings!$C$8,11,1),0),Income!$D$5:$D$504,"Direct",Income!$C$5:$C$504,Dashboard!$C$4)),0) | M18: =IFERROR(IF(Dashboard!$C$4="All",SUMIFS(Income!$L$5:$L$504,Income!$B$5:$B$504,">="&DATE(Settings!$C$8,12,1),Income!$B$5:$B$504,"<="&EOMONTH(DATE(Settings!$C$8,12,1),0),Income!$D$5:$D$504,"Direct"),SUMIFS(Income!$L$5:$L$504,Income!$B$5:$B$504,">="&DATE(Settings!$C$8,12,1),Income!$B$5:$B$504,"<="&EOMONTH(DATE(Settings!$C$8,12,1),0),Income!$D$5:$D$504,"Direct",Income!$C$5:$C$504,Dashboard!$C$4)),0) | N18: =SUM(B18:M18)
A19: Other | B19: =IFERROR(IF(Dashboard!$C$4="All",SUMIFS(Income!$L$5:$L$504,Income!$B$5:$B$504,">="&DATE(Settings!$C$8,1,1),Income!$B$5:$B$504,"<="&EOMONTH(DATE(Settings!$C$8,1,1),0),Income!$D$5:$D$504,"Other"),SUMIFS(Income!$L$5:$L$504,Income!$B$5:$B$504,">="&DATE(Settings!$C$8,1,1),Income!$B$5:$B$504,"<="&EOMONTH(DATE(Settings!$C$8,1,1),0),Income!$D$5:$D$504,"Other",Income!$C$5:$C$504,Dashboard!$C$4)),0) | C19: =IFERROR(IF(Dashboard!$C$4="All",SUMIFS(Income!$L$5:$L$504,Income!$B$5:$B$504,">="&DATE(Settings!$C$8,2,1),Income!$B$5:$B$504,"<="&EOMONTH(DATE(Settings!$C$8,2,1),0),Income!$D$5:$D$504,"Other"),SUMIFS(Income!$L$5:$L$504,Income!$B$5:$B$504,">="&DATE(Settings!$C$8,2,1),Income!$B$5:$B$504,"<="&EOMONTH(DATE(Settings!$C$8,2,1),0),Income!$D$5:$D$504,"Other",Income!$C$5:$C$504,Dashboard!$C$4)),0) | D19: =IFERROR(IF(Dashboard!$C$4="All",SUMIFS(Income!$L$5:$L$504,Income!$B$5:$B$504,">="&DATE(Settings!$C$8,3,1),Income!$B$5:$B$504,"<="&EOMONTH(DATE(Settings!$C$8,3,1),0),Income!$D$5:$D$504,"Other"),SUMIFS(Income!$L$5:$L$504,Income!$B$5:$B$504,">="&DATE(Settings!$C$8,3,1),Income!$B$5:$B$504,"<="&EOMONTH(DATE(Settings!$C$8,3,1),0),Income!$D$5:$D$504,"Other",Income!$C$5:$C$504,Dashboard!$C$4)),0) | E19: =IFERROR(IF(Dashboard!$C$4="All",SUMIFS(Income!$L$5:$L$504,Income!$B$5:$B$504,">="&DATE(Settings!$C$8,4,1),Income!$B$5:$B$504,"<="&EOMONTH(DATE(Settings!$C$8,4,1),0),Income!$D$5:$D$504,"Other"),SUMIFS(Income!$L$5:$L$504,Income!$B$5:$B$504,">="&DATE(Settings!$C$8,4,1),Income!$B$5:$B$504,"<="&EOMONTH(DATE(Settings!$C$8,4,1),0),Income!$D$5:$D$504,"Other",Income!$C$5:$C$504,Dashboard!$C$4)),0) | F19: =IFERROR(IF(Dashboard!$C$4="All",SUMIFS(Income!$L$5:$L$504,Income!$B$5:$B$504,">="&DATE(Settings!$C$8,5,1),Income!$B$5:$B$504,"<="&EOMONTH(DATE(Settings!$C$8,5,1),0),Income!$D$5:$D$504,"Other"),SUMIFS(Income!$L$5:$L$504,Income!$B$5:$B$504,">="&DATE(Settings!$C$8,5,1),Income!$B$5:$B$504,"<="&EOMONTH(DATE(Settings!$C$8,5,1),0),Income!$D$5:$D$504,"Other",Income!$C$5:$C$504,Dashboard!$C$4)),0) | G19: =IFERROR(IF(Dashboard!$C$4="All",SUMIFS(Income!$L$5:$L$504,Income!$B$5:$B$504,">="&DATE(Settings!$C$8,6,1),Income!$B$5:$B$504,"<="&EOMONTH(DATE(Settings!$C$8,6,1),0),Income!$D$5:$D$504,"Other"),SUMIFS(Income!$L$5:$L$504,Income!$B$5:$B$504,">="&DATE(Settings!$C$8,6,1),Income!$B$5:$B$504,"<="&EOMONTH(DATE(Settings!$C$8,6,1),0),Income!$D$5:$D$504,"Other",Income!$C$5:$C$504,Dashboard!$C$4)),0) | H19: =IFERROR(IF(Dashboard!$C$4="All",SUMIFS(Income!$L$5:$L$504,Income!$B$5:$B$504,">="&DATE(Settings!$C$8,7,1),Income!$B$5:$B$504,"<="&EOMONTH(DATE(Settings!$C$8,7,1),0),Income!$D$5:$D$504,"Other"),SUMIFS(Income!$L$5:$L$504,Income!$B$5:$B$504,">="&DATE(Settings!$C$8,7,1),Income!$B$5:$B$504,"<="&EOMONTH(DATE(Settings!$C$8,7,1),0),Income!$D$5:$D$504,"Other",Income!$C$5:$C$504,Dashboard!$C$4)),0) | I19: =IFERROR(IF(Dashboard!$C$4="All",SUMIFS(Income!$L$5:$L$504,Income!$B$5:$B$504,">="&DATE(Settings!$C$8,8,1),Income!$B$5:$B$504,"<="&EOMONTH(DATE(Settings!$C$8,8,1),0),Income!$D$5:$D$504,"Other"),SUMIFS(Income!$L$5:$L$504,Income!$B$5:$B$504,">="&DATE(Settings!$C$8,8,1),Income!$B$5:$B$504,"<="&EOMONTH(DATE(Settings!$C$8,8,1),0),Income!$D$5:$D$504,"Other",Income!$C$5:$C$504,Dashboard!$C$4)),0) | J19: =IFERROR(IF(Dashboard!$C$4="All",SUMIFS(Income!$L$5:$L$504,Income!$B$5:$B$504,">="&DATE(Settings!$C$8,9,1),Income!$B$5:$B$504,"<="&EOMONTH(DATE(Settings!$C$8,9,1),0),Income!$D$5:$D$504,"Other"),SUMIFS(Income!$L$5:$L$504,Income!$B$5:$B$504,">="&DATE(Settings!$C$8,9,1),Income!$B$5:$B$504,"<="&EOMONTH(DATE(Settings!$C$8,9,1),0),Income!$D$5:$D$504,"Other",Income!$C$5:$C$504,Dashboard!$C$4)),0) | K19: =IFERROR(IF(Dashboard!$C$4="All",SUMIFS(Income!$L$5:$L$504,Income!$B$5:$B$504,">="&DATE(Settings!$C$8,10,1),Income!$B$5:$B$504,"<="&EOMONTH(DATE(Settings!$C$8,10,1),0),Income!$D$5:$D$504,"Other"),SUMIFS(Income!$L$5:$L$504,Income!$B$5:$B$504,">="&DATE(Settings!$C$8,10,1),Income!$B$5:$B$504,"<="&EOMONTH(DATE(Settings!$C$8,10,1),0),Income!$D$5:$D$504,"Other",Income!$C$5:$C$504,Dashboard!$C$4)),0) | L19: =IFERROR(IF(Dashboard!$C$4="All",SUMIFS(Income!$L$5:$L$504,Income!$B$5:$B$504,">="&DATE(Settings!$C$8,11,1),Income!$B$5:$B$504,"<="&EOMONTH(DATE(Settings!$C$8,11,1),0),Income!$D$5:$D$504,"Other"),SUMIFS(Income!$L$5:$L$504,Income!$B$5:$B$504,">="&DATE(Settings!$C$8,11,1),Income!$B$5:$B$504,"<="&EOMONTH(DATE(Settings!$C$8,11,1),0),Income!$D$5:$D$504,"Other",Income!$C$5:$C$504,Dashboard!$C$4)),0) | M19: =IFERROR(IF(Dashboard!$C$4="All",SUMIFS(Income!$L$5:$L$504,Income!$B$5:$B$504,">="&DATE(Settings!$C$8,12,1),Income!$B$5:$B$504,"<="&EOMONTH(DATE(Settings!$C$8,12,1),0),Income!$D$5:$D$504,"Other"),SUMIFS(Income!$L$5:$L$504,Income!$B$5:$B$504,">="&DATE(Settings!$C$8,12,1),Income!$B$5:$B$504,"<="&EOMONTH(DATE(Settings!$C$8,12,1),0),Income!$D$5:$D$504,"Other",Income!$C$5:$C$504,Dashboard!$C$4)),0) | N19: =SUM(B19:M19)
A22: Category | B22: YTD amount
A23: Cleaning | B23: =IFERROR(IF(Dashboard!$C$4="All",SUMIFS(Expenses!$F$5:$F$504,Expenses!$D$5:$D$504,"Cleaning",Expenses!$B$5:$B$504,">="&Settings!$C$7),SUMIFS(Expenses!$F$5:$F$504,Expenses!$D$5:$D$504,"Cleaning",Expenses!$B$5:$B$504,">="&Settings!$C$7,Expenses!$C$5:$C$504,Dashboard!$C$4)),0)
A24: Maintenance | B24: =IFERROR(IF(Dashboard!$C$4="All",SUMIFS(Expenses!$F$5:$F$504,Expenses!$D$5:$D$504,"Maintenance",Expenses!$B$5:$B$504,">="&Settings!$C$7),SUMIFS(Expenses!$F$5:$F$504,Expenses!$D$5:$D$504,"Maintenance",Expenses!$B$5:$B$504,">="&Settings!$C$7,Expenses!$C$5:$C$504,Dashboard!$C$4)),0)
A25: Utilities | B25: =IFERROR(IF(Dashboard!$C$4="All",SUMIFS(Expenses!$F$5:$F$504,Expenses!$D$5:$D$504,"Utilities",Expenses!$B$5:$B$504,">="&Settings!$C$7),SUMIFS(Expenses!$F$5:$F$504,Expenses!$D$5:$D$504,"Utilities",Expenses!$B$5:$B$504,">="&Settings!$C$7,Expenses!$C$5:$C$504,Dashboard!$C$4)),0)
A26: Insurance | B26: =IFERROR(IF(Dashboard!$C$4="All",SUMIFS(Expenses!$F$5:$F$504,Expenses!$D$5:$D$504,"Insurance",Expenses!$B$5:$B$504,">="&Settings!$C$7),SUMIFS(Expenses!$F$5:$F$504,Expenses!$D$5:$D$504,"Insurance",Expenses!$B$5:$B$504,">="&Settings!$C$7,Expenses!$C$5:$C$504,Dashboard!$C$4)),0)
A27: Mortgage / Rent | B27: =IFERROR(IF(Dashboard!$C$4="All",SUMIFS(Expenses!$F$5:$F$504,Expenses!$D$5:$D$504,"Mortgage / Rent",Expenses!$B$5:$B$504,">="&Settings!$C$7),SUMIFS(Expenses!$F$5:$F$504,Expenses!$D$5:$D$504,"Mortgage / Rent",Expenses!$B$5:$B$504,">="&Settings!$C$7,Expenses!$C$5:$C$504,Dashboard!$C$4)),0)
A28: Supplies | B28: =IFERROR(IF(Dashboard!$C$4="All",SUMIFS(Expenses!$F$5:$F$504,Expenses!$D$5:$D$504,"Supplies",Expenses!$B$5:$B$504,">="&Settings!$C$7),SUMIFS(Expenses!$F$5:$F$504,Expenses!$D$5:$D$504,"Supplies",Expenses!$B$5:$B$504,">="&Settings!$C$7,Expenses!$C$5:$C$504,Dashboard!$C$4)),0)

Sheet Dashboard
B1: nogvia Finance Tracker
B2: Command center — enter data on Income & Expenses tabs
B4: Property filter | C4: All | E4: =CONCATENATE("Reporting year: ",Settings!$C$8)
B6: Year to date
B7: Income YTD | D7: Expenses YTD | F7: Net P/L | H7: Margin | J7: Cashflow YTD | L7: Mortgage YTD
B8: =IFERROR(IF(Dashboard!$C$4="All",SUMIFS(Income!$L$5:$L$504,Income!$B$5:$B$504,">="&Settings!$C$7,Income!$B$5:$B$504,"<="&DATE(Settings!$C$8,12,31)),SUMIFS(Income!$L$5:$L$504,Income!$B$5:$B$504,">="&Settings!$C$7,Income!$B$5:$B$504,"<="&DATE(Settings!$C$8,12,31),Income!$C$5:$C$504,Dashboard!$C$4)),0) | D8: =IFERROR(IF(Dashboard!$C$4="All",SUMIFS(Expenses!$F$5:$F$504,Expenses!$B$5:$B$504,">="&Settings!$C$7,Expenses!$B$5:$B$504,"<="&DATE(Settings!$C$8,12,31)),SUMIFS(Expenses!$F$5:$F$504,Expenses!$B$5:$B$504,">="&Settings!$C$7,Expenses!$B$5:$B$504,"<="&DATE(Settings!$C$8,12,31),Expenses!$C$5:$C$504,Dashboard!$C$4)),0) | F8: =IFERROR(IFERROR(IF(Dashboard!$C$4="All",SUMIFS(Income!$L$5:$L$504,Income!$B$5:$B$504,">="&Settings!$C$7,Income!$B$5:$B$504,"<="&DATE(Settings!$C$8,12,31)),SUMIFS(Income!$L$5:$L$504,Income!$B$5:$B$504,">="&Settings!$C$7,Income!$B$5:$B$504,"<="&DATE(Settings!$C$8,12,31),Income!$C$5:$C$504,Dashboard!$C$4)),0)-IFERROR(IF(Dashboard!$C$4="All",SUMIFS(Expenses!$F$5:$F$504,Expenses!$B$5:$B$504,">="&Settings!$C$7,Expenses!$B$5:$B$504,"<="&DATE(Settings!$C$8,12,31)),SUMIFS(Expenses!$F$5:$F$504,Expenses!$B$5:$B$504,">="&Settings!$C$7,Expenses!$B$5:$B$504,"<="&DATE(Settings!$C$8,12,31),Expenses!$C$5:$C$504,Dashboard!$C$4)),0),0) | H8: =IFERROR(IF($B$8>0,$F$8/$B$8,0),0) | J8: =IFERROR(IFERROR(IF(Dashboard!$C$4="All",SUMIFS(Income!$L$5:$L$504,Income!$B$5:$B$504,">="&Settings!$C$7,Income!$B$5:$B$504,"<="&DATE(Settings!$C$8,12,31)),SUMIFS(Income!$L$5:$L$504,Income!$B$5:$B$504,">="&Settings!$C$7,Income!$B$5:$B$504,"<="&DATE(Settings!$C$8,12,31),Income!$C$5:$C$504,Dashboard!$C$4)),0)-IFERROR(IF(Dashboard!$C$4="All",SUMIFS(Expenses!$F$5:$F$504,Expenses!$B$5:$B$504,">="&Settings!$C$7,Expenses!$B$5:$B$504,"<="&DATE(Settings!$C$8,12,31)),SUMIFS(Expenses!$F$5:$F$504,Expenses!$B$5:$B$504,">="&Settings!$C$7,Expenses!$B$5:$B$504,"<="&DATE(Settings!$C$8,12,31),Expenses!$C$5:$C$504,Dashboard!$C$4)),0),0) | L8: =IFERROR(IF(Dashboard!$C$4="All",SUMIFS(Expenses!$F$5:$F$504,Expenses!$B$5:$B$504,">="&Settings!$C$7,Expenses!$B$5:$B$504,"<="&DATE(Settings!$C$8,12,31),Expenses!$D$5:$D$504,"Mortgage / Rent"),SUMIFS(Expenses!$F$5:$F$504,Expenses!$B$5:$B$504,">="&Settings!$C$7,Expenses!$B$5:$B$504,"<="&DATE(Settings!$C$8,12,31),Expenses!$D$5:$D$504,"Mortgage / Rent",Expenses!$C$5:$C$504,Dashboard!$C$4)),0)
B23: Revenue by platform (YTD)
B24: Platform | C24: YTD revenue | D24: Share
B25: Airbnb | C25: ==_calc!B6 | D25: =IF($B$8>0,C25/$B$8,0)
B26: VRBO | C26: ==_calc!B7 | D26: =IF($B$8>0,C26/$B$8,0)
B27: Booking.com | C27: ==_calc!B8 | D27: =IF($B$8>0,C27/$B$8,0)
B28: Direct | C28: ==_calc!B9 | D28: =IF($B$8>0,C28/$B$8,0)
B29: Other | C29: ==_calc!B10 | D29: =IF($B$8>0,C29/$B$8,0)
B32: Monthly revenue by platform
B33: Platform | C33: Jan | D33: Feb | E33: Mar | F33: Apr | G33: May | H33: Jun | I33: Jul | J33: Aug | K33: Sep | L33: Oct | M33: Nov | N33: Dec | O33: Total
B34: Airbnb | C34: ==_calc!B15 | D34: ==_calc!C15 | E34: ==_calc!D15 | F34: ==_calc!E15 | G34: ==_calc!F15 | H34: ==_calc!G15 | I34: ==_calc!H15 | J34: ==_calc!I15 | ... O34: ==_calc!N15
B35: VRBO | C35: ==_calc!B16 | D35: ==_calc!C16 | E35: ==_calc!D16 | F35: ==_calc!E16 | G35: ==_calc!F16 | H35: ==_calc!G16 | I35: ==_calc!H16 | J35: ==_calc!I16 | ... O35: ==_calc!N16
B36: Booking.com | C36: ==_calc!B17 | D36: ==_calc!C17 | E36: ==_calc!D17 | F36: ==_calc!E17 | G36: ==_calc!F17 | H36: ==_calc!G17 | I36: ==_calc!H17 | J36: ==_calc!I17 | ... O36: ==_calc!N17
B37: Direct | C37: ==_calc!B18 | D37: ==_calc!C18 | E37: ==_calc!D18 | F37: ==_calc!E18 | G37: ==_calc!F18 | H37: ==_calc!G18 | I37: ==_calc!H18 | J37: ==_calc!I18 | ... O37: ==_calc!N18
B38: Other | C38: ==_calc!B19 | D38: ==_calc!C19 | E38: ==_calc!D19 | F38: ==_calc!E19 | G38: ==_calc!F19 | H38: ==_calc!G19 | I38: ==_calc!H19 | J38: ==_calc!I19 | ... O38: ==_calc!N19
B41: Performance metrics (YTD)
B42: Metric | C42: Value
B43: Booked nights | C43: =IFERROR(IF(Dashboard!$C$4="All",SUMIFS(Income!$G$5:$G$504,Income!$B$5:$B$504,">="&Settings!$C$7,Income!$B$5:$B$504,"<="&DATE(Settings!$C$8,12,31)),SUMIFS(Income!$G$5:$G$504,Income!$B$5:$B$504,">="&Settings!$C$7,Income!$B$5:$B$504,"<="&DATE(Settings!$C$8,12,31),Income!$C$5:$C$504,Dashboard!$C$4)),0)
B44: Unique bookings | C44: =IFERROR(IF(Dashboard!$C$4="All",COUNTIFS(Income!$B$5:$B$504,">="&Settings!$C$7,Income!$B$5:$B$504,"<="&DATE(Settings!$C$8,12,31),Income!$L$5:$L$504,">0"),COUNTIFS(Income!$B$5:$B$504,">="&Settings!$C$7,Income!$B$5:$B$504,"<="&DATE(Settings!$C$8,12,31),Income!$C$5:$C$504,Dashboard!$C$4,Income!$L$5:$L$504,">0")),0)
B45: Occupancy % | C45: =IFERROR(IF(IF(Dashboard!$C$4="All",COUNTIF(Properties!$F$5:$F$54,"Yes")*Settings!$C$10,Settings!$C$10)>0,IFERROR(IF(Dashboard!$C$4="All",SUMIFS(Income!$G$5:$G$504,Income!$B$5:$B$504,">="&Settings!$C$7,Income!$B$5:$B$504,"<="&DATE(Settings!$C$8,12,31)),SUMIFS(Income!$G$5:$G$504,Income!$B$5:$B$504,">="&Settings!$C$7,Income!$B$5:$B$504,"<="&DATE(Settings!$C$8,12,31),Income!$C$5:$C$504,Dashboard!$C$4)),0)/IF(Dashboard!$C$4="All",COUNTIF(Properties!$F$5:$F$54,"Yes")*Settings!$C$10,Settings!$C$10),0),0)
B46: ADR | C46: =IFERROR(IF(IFERROR(IF(Dashboard!$C$4="All",SUMIFS(Income!$G$5:$G$504,Income!$B$5:$B$504,">="&Settings!$C$7,Income!$B$5:$B$504,"<="&DATE(Settings!$C$8,12,31)),SUMIFS(Income!$G$5:$G$504,Income!$B$5:$B$504,">="&Settings!$C$7,Income!$B$5:$B$504,"<="&DATE(Settings!$C$8,12,31),Income!$C$5:$C$504,Dashboard!$C$4)),0)>0,IFERROR(IF(Dashboard!$C$4="All",SUMIFS(Income!$L$5:$L$504,Income!$B$5:$B$504,">="&Settings!$C$7,Income!$B$5:$B$504,"<="&DATE(Settings!$C$8,12,31)),SUMIFS(Income!$L$5:$L$504,Income!$B$5:$B$504,">="&Settings!$C$7,Income!$B$5:$B$504,"<="&DATE(Settings!$C$8,12,31),Income!$C$5:$C$504,Dashboard!$C$4)),0)/IFERROR(IF(Dashboard!$C$4="All",SUMIFS(Income!$G$5:$G$504,Income!$B$5:$B$504,">="&Settings!$C$7,Income!$B$5:$B$504,"<="&DATE(Settings!$C$8,12,31)),SUMIFS(Income!$G$5:$G$504,Income!$B$5:$B$504,">="&Settings!$C$7,Income!$B$5:$B$504,"<="&DATE(Settings!$C$8,12,31),Income!$C$5:$C$504,Dashboard!$C$4)),0),0),0)
B47: RevPAR | C47: =IFERROR(IF(IF(Dashboard!$C$4="All",COUNTIF(Properties!$F$5:$F$54,"Yes")*Settings!$C$10,Settings!$C$10)>0,IFERROR(IF(Dashboard!$C$4="All",SUMIFS(Income!$L$5:$L$504,Income!$B$5:$B$504,">="&Settings!$C$7,Income!$B$5:$B$504,"<="&DATE(Settings!$C$8,12,31)),SUMIFS(Income!$L$5:$L$504,Income!$B$5:$B$504,">="&Settings!$C$7,Income!$B$5:$B$504,"<="&DATE(Settings!$C$8,12,31),Income!$C$5:$C$504,Dashboard!$C$4)),0)/IF(Dashboard!$C$4="All",COUNTIF(Properties!$F$5:$F$54,"Yes")*Settings!$C$10,Settings!$C$10),0),0)
B48: Platform fees | C48: =IFERROR(IF(Dashboard!$C$4="All",SUMIFS(Income!$J$5:$J$504,Income!$B$5:$B$504,">="&Settings!$C$7,Income!$B$5:$B$504,"<="&DATE(Settings!$C$8,12,31)),SUMIFS(Income!$J$5:$J$504,Income!$B$5:$B$504,">="&Settings!$C$7,Income!$B$5:$B$504,"<="&DATE(Settings!$C$8,12,31),Income!$C$5:$C$504,Dashboard!$C$4)),0)
B51: Top expense categories (YTD)
B52: Category | C52: Amount | D52: Share
B53: Cleaning | C53: =IFERROR(IF(Dashboard!$C$4="All",SUMIFS(Expenses!$F$5:$F$504,Expenses!$D$5:$D$504,"Cleaning",Expenses!$B$5:$B$504,">="&Settings!$C$7),SUMIFS(Expenses!$F$5:$F$504,Expenses!$D$5:$D$504,"Cleaning",Expenses!$B$5:$B$504,">="&Settings!$C$7,Expenses!$C$5:$C$504,Dashboard!$C$4)),0) | D53: =IF($D$8>0,C53/$D$8,0)
B54: Maintenance | C54: =IFERROR(IF(Dashboard!$C$4="All",SUMIFS(Expenses!$F$5:$F$504,Expenses!$D$5:$D$504,"Maintenance",Expenses!$B$5:$B$504,">="&Settings!$C$7),SUMIFS(Expenses!$F$5:$F$504,Expenses!$D$5:$D$504,"Maintenance",Expenses!$B$5:$B$504,">="&Settings!$C$7,Expenses!$C$5:$C$504,Dashboard!$C$4)),0) | D54: =IF($D$8>0,C54/$D$8,0)
B55: Utilities | C55: =IFERROR(IF(Dashboard!$C$4="All",SUMIFS(Expenses!$F$5:$F$504,Expenses!$D$5:$D$504,"Utilities",Expenses!$B$5:$B$504,">="&Settings!$C$7),SUMIFS(Expenses!$F$5:$F$504,Expenses!$D$5:$D$504,"Utilities",Expenses!$B$5:$B$504,">="&Settings!$C$7,Expenses!$C$5:$C$504,Dashboard!$C$4)),0) | D55: =IF($D$8>0,C55/$D$8,0)
B56: Insurance | C56: =IFERROR(IF(Dashboard!$C$4="All",SUMIFS(Expenses!$F$5:$F$504,Expenses!$D$5:$D$504,"Insurance",Expenses!$B$5:$B$504,">="&Settings!$C$7),SUMIFS(Expenses!$F$5:$F$504,Expenses!$D$5:$D$504,"Insurance",Expenses!$B$5:$B$504,">="&Settings!$C$7,Expenses!$C$5:$C$504,Dashboard!$C$4)),0) | D56: =IF($D$8>0,C56/$D$8,0)
B57: Mortgage / Rent | C57: =IFERROR(IF(Dashboard!$C$4="All",SUMIFS(Expenses!$F$5:$F$504,Expenses!$D$5:$D$504,"Mortgage / Rent",Expenses!$B$5:$B$504,">="&Settings!$C$7),SUMIFS(Expenses!$F$5:$F$504,Expenses!$D$5:$D$504,"Mortgage / Rent",Expenses!$B$5:$B$504,">="&Settings!$C$7,Expenses!$C$5:$C$504,Dashboard!$C$4)),0) | D57: =IF($D$8>0,C57/$D$8,0)
B58: Supplies | C58: =IFERROR(IF(Dashboard!$C$4="All",SUMIFS(Expenses!$F$5:$F$504,Expenses!$D$5:$D$504,"Supplies",Expenses!$B$5:$B$504,">="&Settings!$C$7),SUMIFS(Expenses!$F$5:$F$504,Expenses!$D$5:$D$504,"Supplies",Expenses!$B$5:$B$504,">="&Settings!$C$7,Expenses!$C$5:$C$504,Dashboard!$C$4)),0) | D58: =IF($D$8>0,C58/$D$8,0)

Sheet Monthly P&L
A1: Monthly P&L
A2: Profit & loss by month for the reporting year
B5: Metric | C5: Jan | D5: Feb | E5: Mar | F5: Apr | G5: May | H5: Jun | I5: Jul | J5: Aug | K5: Sep | L5: Oct | M5: Nov | N5: Dec | O5: Total
B6: Revenue | C6: =IFERROR(IF(Dashboard!$C$4="All",SUMIFS(Income!$L$5:$L$504,Income!$B$5:$B$504,">="&DATE(Settings!$C$8,1,1),Income!$B$5:$B$504,"<="&EOMONTH(DATE(Settings!$C$8,1,1),0)),SUMIFS(Income!$L$5:$L$504,Income!$B$5:$B$504,">="&DATE(Settings!$C$8,1,1),Income!$B$5:$B$504,"<="&EOMONTH(DATE(Settings!$C$8,1,1),0),Income!$C$5:$C$504,Dashboard!$C$4)),0) | D6: =IFERROR(IF(Dashboard!$C$4="All",SUMIFS(Income!$L$5:$L$504,Income!$B$5:$B$504,">="&DATE(Settings!$C$8,2,1),Income!$B$5:$B$504,"<="&EOMONTH(DATE(Settings!$C$8,2,1),0)),SUMIFS(Income!$L$5:$L$504,Income!$B$5:$B$504,">="&DATE(Settings!$C$8,2,1),Income!$B$5:$B$504,"<="&EOMONTH(DATE(Settings!$C$8,2,1),0),Income!$C$5:$C$504,Dashboard!$C$4)),0) | E6: =IFERROR(IF(Dashboard!$C$4="All",SUMIFS(Income!$L$5:$L$504,Income!$B$5:$B$504,">="&DATE(Settings!$C$8,3,1),Income!$B$5:$B$504,"<="&EOMONTH(DATE(Settings!$C$8,3,1),0)),SUMIFS(Income!$L$5:$L$504,Income!$B$5:$B$504,">="&DATE(Settings!$C$8,3,1),Income!$B$5:$B$504,"<="&EOMONTH(DATE(Settings!$C$8,3,1),0),Income!$C$5:$C$504,Dashboard!$C$4)),0) | F6: =IFERROR(IF(Dashboard!$C$4="All",SUMIFS(Income!$L$5:$L$504,Income!$B$5:$B$504,">="&DATE(Settings!$C$8,4,1),Income!$B$5:$B$504,"<="&EOMONTH(DATE(Settings!$C$8,4,1),0)),SUMIFS(Income!$L$5:$L$504,Income!$B$5:$B$504,">="&DATE(Settings!$C$8,4,1),Income!$B$5:$B$504,"<="&EOMONTH(DATE(Settings!$C$8,4,1),0),Income!$C$5:$C$504,Dashboard!$C$4)),0) | G6: =IFERROR(IF(Dashboard!$C$4="All",SUMIFS(Income!$L$5:$L$504,Income!$B$5:$B$504,">="&DATE(Settings!$C$8,5,1),Income!$B$5:$B$504,"<="&EOMONTH(DATE(Settings!$C$8,5,1),0)),SUMIFS(Income!$L$5:$L$504,Income!$B$5:$B$504,">="&DATE(Settings!$C$8,5,1),Income!$B$5:$B$504,"<="&EOMONTH(DATE(Settings!$C$8,5,1),0),Income!$C$5:$C$504,Dashboard!$C$4)),0) | H6: =IFERROR(IF(Dashboard!$C$4="All",SUMIFS(Income!$L$5:$L$504,Income!$B$5:$B$504,">="&DATE(Settings!$C$8,6,1),Income!$B$5:$B$504,"<="&EOMONTH(DATE(Settings!$C$8,6,1),0)),SUMIFS(Income!$L$5:$L$504,Income!$B$5:$B$504,">="&DATE(Settings!$C$8,6,1),Income!$B$5:$B$504,"<="&EOMONTH(DATE(Settings!$C$8,6,1),0),Income!$C$5:$C$504,Dashboard!$C$4)),0) | I6: =IFERROR(IF(Dashboard!$C$4="All",SUMIFS(Income!$L$5:$L$504,Income!$B$5:$B$504,">="&DATE(Settings!$C$8,7,1),Income!$B$5:$B$504,"<="&EOMONTH(DATE(Settings!$C$8,7,1),0)),SUMIFS(Income!$L$5:$L$504,Income!$B$5:$B$504,">="&DATE(Settings!$C$8,7,1),Income!$B$5:$B$504,"<="&EOMONTH(DATE(Settings!$C$8,7,1),0),Income!$C$5:$C$504,Dashboard!$C$4)),0) | J6: =IFERROR(IF(Dashboard!$C$4="All",SUMIFS(Income!$L$5:$L$504,Income!$B$5:$B$504,">="&DATE(Settings!$C$8,8,1),Income!$B$5:$B$504,"<="&EOMONTH(DATE(Settings!$C$8,8,1),0)),SUMIFS(Income!$L$5:$L$504,Income!$B$5:$B$504,">="&DATE(Settings!$C$8,8,1),Income!$B$5:$B$504,"<="&EOMONTH(DATE(Settings!$C$8,8,1),0),Income!$C$5:$C$504,Dashboard!$C$4)),0) | K6: =IFERROR(IF(Dashboard!$C$4="All",SUMIFS(Income!$L$5:$L$504,Income!$B$5:$B$504,">="&DATE(Settings!$C$8,9,1),Income!$B$5:$B$504,"<="&EOMONTH(DATE(Settings!$C$8,9,1),0)),SUMIFS(Income!$L$5:$L$504,Income!$B$5:$B$504,">="&DATE(Settings!$C$8,9,1),Income!$B$5:$B$504,"<="&EOMONTH(DATE(Settings!$C$8,9,1),0),Income!$C$5:$C$504,Dashboard!$C$4)),0) | L6: =IFERROR(IF(Dashboard!$C$4="All",SUMIFS(Income!$L$5:$L$504,Income!$B$5:$B$504,">="&DATE(Settings!$C$8,10,1),Income!$B$5:$B$504,"<="&EOMONTH(DATE(Settings!$C$8,10,1),0)),SUMIFS(Income!$L$5:$L$504,Income!$B$5:$B$504,">="&DATE(Settings!$C$8,10,1),Income!$B$5:$B$504,"<="&EOMONTH(DATE(Settings!$C$8,10,1),0),Income!$C$5:$C$504,Dashboard!$C$4)),0) | M6: =IFERROR(IF(Dashboard!$C$4="All",SUMIFS(Income!$L$5:$L$504,Income!$B$5:$B$504,">="&DATE(Settings!$C$8,11,1),Income!$B$5:$B$504,"<="&EOMONTH(DATE(Settings!$C$8,11,1),0)),SUMIFS(Income!$L$5:$L$504,Income!$B$5:$B$504,">="&DATE(Settings!$C$8,11,1),Income!$B$5:$B$504,"<="&EOMONTH(DATE(Settings!$C$8,11,1),0),Income!$C$5:$C$504,Dashboard!$C$4)),0) | N6: =IFERROR(IF(Dashboard!$C$4="All",SUMIFS(Income!$L$5:$L$504,Income!$B$5:$B$504,">="&DATE(Settings!$C$8,12,1),Income!$B$5:$B$504,"<="&EOMONTH(DATE(Settings!$C$8,12,1),0)),SUMIFS(Income!$L$5:$L$504,Income!$B$5:$B$504,">="&DATE(Settings!$C$8,12,1),Income!$B$5:$B$504,"<="&EOMONTH(DATE(Settings!$C$8,12,1),0),Income!$C$5:$C$504,Dashboard!$C$4)),0) | O6: =SUM(C6:N6)
B7: Expenses | C7: =IFERROR(IF(Dashboard!$C$4="All",SUMIFS(Expenses!$F$5:$F$504,Expenses!$B$5:$B$504,">="&DATE(Settings!$C$8,1,1),Expenses!$B$5:$B$504,"<="&EOMONTH(DATE(Settings!$C$8,1,1),0)),SUMIFS(Expenses!$F$5:$F$504,Expenses!$B$5:$B$504,">="&DATE(Settings!$C$8,1,1),Expenses!$B$5:$B$504,"<="&EOMONTH(DATE(Settings!$C$8,1,1),0),Expenses!$C$5:$C$504,Dashboard!$C$4)),0) | D7: =IFERROR(IF(Dashboard!$C$4="All",SUMIFS(Expenses!$F$5:$F$504,Expenses!$B$5:$B$504,">="&DATE(Settings!$C$8,2,1),Expenses!$B$5:$B$504,"<="&EOMONTH(DATE(Settings!$C$8,2,1),0)),SUMIFS(Expenses!$F$5:$F$504,Expenses!$B$5:$B$504,">="&DATE(Settings!$C$8,2,1),Expenses!$B$5:$B$504,"<="&EOMONTH(DATE(Settings!$C$8,2,1),0),Expenses!$C$5:$C$504,Dashboard!$C$4)),0) | E7: =IFERROR(IF(Dashboard!$C$4="All",SUMIFS(Expenses!$F$5:$F$504,Expenses!$B$5:$B$504,">="&DATE(Settings!$C$8,3,1),Expenses!$B$5:$B$504,"<="&EOMONTH(DATE(Settings!$C$8,3,1),0)),SUMIFS(Expenses!$F$5:$F$504,Expenses!$B$5:$B$504,">="&DATE(Settings!$C$8,3,1),Expenses!$B$5:$B$504,"<="&EOMONTH(DATE(Settings!$C$8,3,1),0),Expenses!$C$5:$C$504,Dashboard!$C$4)),0) | F7: =IFERROR(IF(Dashboard!$C$4="All",SUMIFS(Expenses!$F$5:$F$504,Expenses!$B$5:$B$504,">="&DATE(Settings!$C$8,4,1),Expenses!$B$5:$B$504,"<="&EOMONTH(DATE(Settings!$C$8,4,1),0)),SUMIFS(Expenses!$F$5:$F$504,Expenses!$B$5:$B$504,">="&DATE(Settings!$C$8,4,1),Expenses!$B$5:$B$504,"<="&EOMONTH(DATE(Settings!$C$8,4,1),0),Expenses!$C$5:$C$504,Dashboard!$C$4)),0) | G7: =IFERROR(IF(Dashboard!$C$4="All",SUMIFS(Expenses!$F$5:$F$504,Expenses!$B$5:$B$504,">="&DATE(Settings!$C$8,5,1),Expenses!$B$5:$B$504,"<="&EOMONTH(DATE(Settings!$C$8,5,1),0)),SUMIFS(Expenses!$F$5:$F$504,Expenses!$B$5:$B$504,">="&DATE(Settings!$C$8,5,1),Expenses!$B$5:$B$504,"<="&EOMONTH(DATE(Settings!$C$8,5,1),0),Expenses!$C$5:$C$504,Dashboard!$C$4)),0) | H7: =IFERROR(IF(Dashboard!$C$4="All",SUMIFS(Expenses!$F$5:$F$504,Expenses!$B$5:$B$504,">="&DATE(Settings!$C$8,6,1),Expenses!$B$5:$B$504,"<="&EOMONTH(DATE(Settings!$C$8,6,1),0)),SUMIFS(Expenses!$F$5:$F$504,Expenses!$B$5:$B$504,">="&DATE(Settings!$C$8,6,1),Expenses!$B$5:$B$504,"<="&EOMONTH(DATE(Settings!$C$8,6,1),0),Expenses!$C$5:$C$504,Dashboard!$C$4)),0) | I7: =IFERROR(IF(Dashboard!$C$4="All",SUMIFS(Expenses!$F$5:$F$504,Expenses!$B$5:$B$504,">="&DATE(Settings!$C$8,7,1),Expenses!$B$5:$B$504,"<="&EOMONTH(DATE(Settings!$C$8,7,1),0)),SUMIFS(Expenses!$F$5:$F$504,Expenses!$B$5:$B$504,">="&DATE(Settings!$C$8,7,1),Expenses!$B$5:$B$504,"<="&EOMONTH(DATE(Settings!$C$8,7,1),0),Expenses!$C$5:$C$504,Dashboard!$C$4)),0) | J7: =IFERROR(IF(Dashboard!$C$4="All",SUMIFS(Expenses!$F$5:$F$504,Expenses!$B$5:$B$504,">="&DATE(Settings!$C$8,8,1),Expenses!$B$5:$B$504,"<="&EOMONTH(DATE(Settings!$C$8,8,1),0)),SUMIFS(Expenses!$F$5:$F$504,Expenses!$B$5:$B$504,">="&DATE(Settings!$C$8,8,1),Expenses!$B$5:$B$504,"<="&EOMONTH(DATE(Settings!$C$8,8,1),0),Expenses!$C$5:$C$504,Dashboard!$C$4)),0) | K7: =IFERROR(IF(Dashboard!$C$4="All",SUMIFS(Expenses!$F$5:$F$504,Expenses!$B$5:$B$504,">="&DATE(Settings!$C$8,9,1),Expenses!$B$5:$B$504,"<="&EOMONTH(DATE(Settings!$C$8,9,1),0)),SUMIFS(Expenses!$F$5:$F$504,Expenses!$B$5:$B$504,">="&DATE(Settings!$C$8,9,1),Expenses!$B$5:$B$504,"<="&EOMONTH(DATE(Settings!$C$8,9,1),0),Expenses!$C$5:$C$504,Dashboard!$C$4)),0) | L7: =IFERROR(IF(Dashboard!$C$4="All",SUMIFS(Expenses!$F$5:$F$504,Expenses!$B$5:$B$504,">="&DATE(Settings!$C$8,10,1),Expenses!$B$5:$B$504,"<="&EOMONTH(DATE(Settings!$C$8,10,1),0)),SUMIFS(Expenses!$F$5:$F$504,Expenses!$B$5:$B$504,">="&DATE(Settings!$C$8,10,1),Expenses!$B$5:$B$504,"<="&EOMONTH(DATE(Settings!$C$8,10,1),0),Expenses!$C$5:$C$504,Dashboard!$C$4)),0) | M7: =IFERROR(IF(Dashboard!$C$4="All",SUMIFS(Expenses!$F$5:$F$504,Expenses!$B$5:$B$504,">="&DATE(Settings!$C$8,11,1),Expenses!$B$5:$B$504,"<="&EOMONTH(DATE(Settings!$C$8,11,1),0)),SUMIFS(Expenses!$F$5:$F$504,Expenses!$B$5:$B$504,">="&DATE(Settings!$C$8,11,1),Expenses!$B$5:$B$504,"<="&EOMONTH(DATE(Settings!$C$8,11,1),0),Expenses!$C$5:$C$504,Dashboard!$C$4)),0) | N7: =IFERROR(IF(Dashboard!$C$4="All",SUMIFS(Expenses!$F$5:$F$504,Expenses!$B$5:$B$504,">="&DATE(Settings!$C$8,12,1),Expenses!$B$5:$B$504,"<="&EOMONTH(DATE(Settings!$C$8,12,1),0)),SUMIFS(Expenses!$F$5:$F$504,Expenses!$B$5:$B$504,">="&DATE(Settings!$C$8,12,1),Expenses!$B$5:$B$504,"<="&EOMONTH(DATE(Settings!$C$8,12,1),0),Expenses!$C$5:$C$504,Dashboard!$C$4)),0) | O7: =SUM(C7:N7)
B8: Net profit | C8: =C6-C7 | D8: =D6-D7 | E8: =E6-E7 | F8: =F6-F7 | G8: =G6-G7 | H8: =H6-H7 | I8: =I6-I7 | J8: =J6-J7 | ... N8: =N6-N7 | O8: =SUM(C8:N8)

Sheet Cashflow
A1: Cashflow
A2: Cash in vs cash out — monthly view
B5: Metric | C5: Jan | D5: Feb | E5: Mar | F5: Apr | G5: May | H5: Jun | I5: Jul | J5: Aug | K5: Sep | L5: Oct | M5: Nov | N5: Dec | O5: Total
B6: Cash in | C6: ='Monthly P&L'!C6 | D6: ='Monthly P&L'!D6 | E6: ='Monthly P&L'!E6 | F6: ='Monthly P&L'!F6 | G6: ='Monthly P&L'!G6 | H6: ='Monthly P&L'!H6 | I6: ='Monthly P&L'!I6 | J6: ='Monthly P&L'!J6 | ... N6: ='Monthly P&L'!N6 | O6: =SUM(C6:N6)
B7: Cash out | C7: ='Monthly P&L'!C7 | D7: ='Monthly P&L'!D7 | E7: ='Monthly P&L'!E7 | F7: ='Monthly P&L'!F7 | G7: ='Monthly P&L'!G7 | H7: ='Monthly P&L'!H7 | I7: ='Monthly P&L'!I7 | J7: ='Monthly P&L'!J7 | ... N7: ='Monthly P&L'!N7 | O7: =SUM(C7:N7)
B8: Net cashflow | C8: =C6-C7 | D8: =D6-D7 | E8: =E6-E7 | F8: =F6-F7 | G8: =G6-G7 | H8: =H6-H7 | I8: =I6-I7 | J8: =J6-J7 | ... N8: =N6-N7 | O8: =SUM(C8:N8)
